{
  "1": [
    "Instrumental:",
    "   <b>Bm</b> <b>G/B</b>  <b>A</b>"
    ],
  "2":[
    "   <b>D</b>      <b>A</b>          <b>Bm</b>        <b>A</b>",
    "o sol, a lua,   estrelas e o mar",
    "            <b>Em</b>          <b>Bm</b>       <b>A4</b> <b>A</b>",
    "nada se compara ante a sua formosura"
    ],
  "3":[
    "    <b>D</b>           <b>A</b>         <b>Bm</b>          <b>A</b>",
    "os homens, os reinos, principados e potestades",
    "    <b>Em</b>             <b>Bm</b>     <b>A4</b>     <b>A</b>",
    "se prostram ante a sua majestade"
    ],
  "4":[
    "                 <b>Em</b> ",
    "porque d'Ele por Ele para",
    "<b>Bm</b>                <b>A</b>",
    "Ele s찾o todas as coisas",
    "                 <b>Em</b> ",
    "porque d'Ele por Ele para",
    "<b>Bm</b>                <b>A</b>",
    "Ele s찾o todas as coisas"
   ],
  "5":[
    "              <b>Bm</b>   <b>G</b>      <b>D</b>     <b>A</b>",
    "s처 me resta te adorar, te adorar",
    "             <b>Bm</b>   <b>G</b>       <b>D</b>    <b>A</b>",
    "eu s처 quero te adorar, te adorar",
    "              <b>Bm</b>   <b>G</b>       <b>D</b>     <b>A</b>",
    "eu nasci pra te adorar, te adorar"
    ],
  "6":[
    "               <b>Em</b>      <b>Bm</b>            <b>A</b>",
    "e dizer que te amo, te amo te amo, te amo",
    "                <b>G</b>     <b>Bm</b>             <b>A</b>",
    "e dizer que te amo, te amo te amo, te amo"
  ]
}